pyzipei/__init__.py
pyzipei/pyzipei.py
pyzipei-0.1.0.data/scripts/PyZipEI
pyzipei-0.1.0.dist-info/DESCRIPTION.rst
pyzipei-0.1.0.dist-info/METADATA
pyzipei-0.1.0.dist-info/RECORD
pyzipei-0.1.0.dist-info/WHEEL
pyzipei-0.1.0.dist-info/metadata.json
pyzipei-0.1.0.dist-info/top_level.txt
