Metadata-Version: 2.0
Name: pyzipei
Version: 0.1.0
Summary: A utility library for retrieving electrical rates from OpenEI.org
Home-page: https://gitlab.com/pentairiot/PyZipEI
Author: PentairIoT
Author-email: pentairiot@gmail.com
License: UNKNOWN
Platform: UNKNOWN
Classifier: Programming Language :: Python :: 3
Classifier: License :: OSI Approved :: MIT License
Classifier: Operating System :: OS Independent
Requires-Dist: requests
Requires-Dist: bs4
